{
  "absolutePath": "contracts/interfaces/IErrors.sol",
  "id": 7729,
  "exportedSymbols": {
    "IErrors": [
      7728
    ]
  },
  "nodeType": "SourceUnit",
  "src": "32:3260:28",
  "nodes": [
    {
      "id": 7624,
      "nodeType": "PragmaDirective",
      "src": "32:24:28",
      "nodes": [],
      "literals": [
        "solidity",
        "^",
        "0.8",
        ".15"
      ]
    },
    {
      "id": 7728,
      "nodeType": "ContractDefinition",
      "src": "75:3216:28",
      "nodes": [
        {
          "id": 7632,
          "nodeType": "ErrorDefinition",
          "src": "269:47:28",
          "nodes": [],
          "documentation": {
            "id": 7626,
            "nodeType": "StructuredDocumentation",
            "src": "99:165:28",
            "text": "@dev Only `owner` has a privilege, but the `sender` was provided.\n @param sender Sender address.\n @param owner Required sender address as an owner."
          },
          "errorSelector": "a43d6ada",
          "name": "OwnerOnly",
          "nameLocation": "275:9:28",
          "parameters": {
            "id": 7631,
            "nodeType": "ParameterList",
            "parameters": [
              {
                "constant": false,
                "id": 7628,
                "mutability": "mutable",
                "name": "sender",
                "nameLocation": "293:6:28",
                "nodeType": "VariableDeclaration",
                "scope": 7632,
                "src": "285:14:28",
                "stateVariable": false,
                "storageLocation": "default",
                "typeDescriptions": {
                  "typeIdentifier": "t_address",
                  "typeString": "address"
                },
                "typeName": {
                  "id": 7627,
                  "name": "address",
                  "nodeType": "ElementaryTypeName",
                  "src": "285:7:28",
                  "stateMutability": "nonpayable",
                  "typeDescriptions": {
                    "typeIdentifier": "t_address",
                    "typeString": "address"
                  }
                },
                "visibility": "internal"
              },
              {
                "constant": false,
                "id": 7630,
                "mutability": "mutable",
                "name": "owner",
                "nameLocation": "309:5:28",
                "nodeType": "VariableDeclaration",
                "scope": 7632,
                "src": "301:13:28",
                "stateVariable": false,
                "storageLocation": "default",
                "typeDescriptions": {
                  "typeIdentifier": "t_address",
                  "typeString": "address"
                },
                "typeName": {
                  "id": 7629,
                  "name": "address",
                  "nodeType": "ElementaryTypeName",
                  "src": "301:7:28",
                  "stateMutability": "nonpayable",
                  "typeDescriptions": {
                    "typeIdentifier": "t_address",
                    "typeString": "address"
                  }
                },
                "visibility": "internal"
              }
            ],
            "src": "284:31:28"
          }
        },
        {
          "id": 7635,
          "nodeType": "ErrorDefinition",
          "src": "358:20:28",
          "nodes": [],
          "documentation": {
            "id": 7633,
            "nodeType": "StructuredDocumentation",
            "src": "322:31:28",
            "text": "@dev Provided zero address."
          },
          "errorSelector": "d92e233d",
          "name": "ZeroAddress",
          "nameLocation": "364:11:28",
          "parameters": {
            "id": 7634,
            "nodeType": "ParameterList",
            "parameters": [],
            "src": "375:2:28"
          }
        },
        {
          "id": 7638,
          "nodeType": "ErrorDefinition",
          "src": "447:18:28",
          "nodes": [],
          "documentation": {
            "id": 7636,
            "nodeType": "StructuredDocumentation",
            "src": "384:58:28",
            "text": "@dev Zero value when it has to be different from zero."
          },
          "errorSelector": "7c946ed7",
          "name": "ZeroValue",
          "nameLocation": "453:9:28",
          "parameters": {
            "id": 7637,
            "nodeType": "ParameterList",
            "parameters": [],
            "src": "462:2:28"
          }
        },
        {
          "id": 7641,
          "nodeType": "ErrorDefinition",
          "src": "523:21:28",
          "nodes": [],
          "documentation": {
            "id": 7639,
            "nodeType": "StructuredDocumentation",
            "src": "471:47:28",
            "text": "@dev Non-zero value when it has to be zero."
          },
          "errorSelector": "e320176b",
          "name": "NonZeroValue",
          "nameLocation": "529:12:28",
          "parameters": {
            "id": 7640,
            "nodeType": "ParameterList",
            "parameters": [],
            "src": "541:2:28"
          }
        },
        {
          "id": 7648,
          "nodeType": "ErrorDefinition",
          "src": "715:63:28",
          "nodes": [],
          "documentation": {
            "id": 7642,
            "nodeType": "StructuredDocumentation",
            "src": "550:160:28",
            "text": "@dev Wrong length of two arrays.\n @param numValues1 Number of values in a first array.\n @param numValues2 Numberf of values in a second array."
          },
          "errorSelector": "8151c110",
          "name": "WrongArrayLength",
          "nameLocation": "721:16:28",
          "parameters": {
            "id": 7647,
            "nodeType": "ParameterList",
            "parameters": [
              {
                "constant": false,
                "id": 7644,
                "mutability": "mutable",
                "name": "numValues1",
                "nameLocation": "746:10:28",
                "nodeType": "VariableDeclaration",
                "scope": 7648,
                "src": "738:18:28",
                "stateVariable": false,
                "storageLocation": "default",
                "typeDescriptions": {
                  "typeIdentifier": "t_uint256",
                  "typeString": "uint256"
                },
                "typeName": {
                  "id": 7643,
                  "name": "uint256",
                  "nodeType": "ElementaryTypeName",
                  "src": "738:7:28",
                  "typeDescriptions": {
                    "typeIdentifier": "t_uint256",
                    "typeString": "uint256"
                  }
                },
                "visibility": "internal"
              },
              {
                "constant": false,
                "id": 7646,
                "mutability": "mutable",
                "name": "numValues2",
                "nameLocation": "766:10:28",
                "nodeType": "VariableDeclaration",
                "scope": 7648,
                "src": "758:18:28",
                "stateVariable": false,
                "storageLocation": "default",
                "typeDescriptions": {
                  "typeIdentifier": "t_uint256",
                  "typeString": "uint256"
                },
                "typeName": {
                  "id": 7645,
                  "name": "uint256",
                  "nodeType": "ElementaryTypeName",
                  "src": "758:7:28",
                  "typeDescriptions": {
                    "typeIdentifier": "t_uint256",
                    "typeString": "uint256"
                  }
                },
                "visibility": "internal"
              }
            ],
            "src": "737:40:28"
          }
        },
        {
          "id": 7655,
          "nodeType": "ErrorDefinition",
          "src": "896:46:28",
          "nodes": [],
          "documentation": {
            "id": 7649,
            "nodeType": "StructuredDocumentation",
            "src": "784:107:28",
            "text": "@dev Value overflow.\n @param provided Overflow value.\n @param max Maximum possible value."
          },
          "errorSelector": "7ae59685",
          "name": "Overflow",
          "nameLocation": "902:8:28",
          "parameters": {
            "id": 7654,
            "nodeType": "ParameterList",
            "parameters": [
              {
                "constant": false,
                "id": 7651,
                "mutability": "mutable",
                "name": "provided",
                "nameLocation": "919:8:28",
                "nodeType": "VariableDeclaration",
                "scope": 7655,
                "src": "911:16:28",
                "stateVariable": false,
                "storageLocation": "default",
                "typeDescriptions": {
                  "typeIdentifier": "t_uint256",
                  "typeString": "uint256"
                },
                "typeName": {
                  "id": 7650,
                  "name": "uint256",
                  "nodeType": "ElementaryTypeName",
                  "src": "911:7:28",
                  "typeDescriptions": {
                    "typeIdentifier": "t_uint256",
                    "typeString": "uint256"
                  }
                },
                "visibility": "internal"
              },
              {
                "constant": false,
                "id": 7653,
                "mutability": "mutable",
                "name": "max",
                "nameLocation": "937:3:28",
                "nodeType": "VariableDeclaration",
                "scope": 7655,
                "src": "929:11:28",
                "stateVariable": false,
                "storageLocation": "default",
                "typeDescriptions": {
                  "typeIdentifier": "t_uint256",
                  "typeString": "uint256"
                },
                "typeName": {
                  "id": 7652,
                  "name": "uint256",
                  "nodeType": "ElementaryTypeName",
                  "src": "929:7:28",
                  "typeDescriptions": {
                    "typeIdentifier": "t_uint256",
                    "typeString": "uint256"
                  }
                },
                "visibility": "internal"
              }
            ],
            "src": "910:31:28"
          }
        },
        {
          "id": 7660,
          "nodeType": "ErrorDefinition",
          "src": "1026:39:28",
          "nodes": [],
          "documentation": {
            "id": 7656,
            "nodeType": "StructuredDocumentation",
            "src": "948:73:28",
            "text": "@dev Token is non-transferable.\n @param account Token address."
          },
          "errorSelector": "9c21e7b2",
          "name": "NonTransferable",
          "nameLocation": "1032:15:28",
          "parameters": {
            "id": 7659,
            "nodeType": "ParameterList",
            "parameters": [
              {
                "constant": false,
                "id": 7658,
                "mutability": "mutable",
                "name": "account",
                "nameLocation": "1056:7:28",
                "nodeType": "VariableDeclaration",
                "scope": 7660,
                "src": "1048:15:28",
                "stateVariable": false,
                "storageLocation": "default",
                "typeDescriptions": {
                  "typeIdentifier": "t_address",
                  "typeString": "address"
                },
                "typeName": {
                  "id": 7657,
                  "name": "address",
                  "nodeType": "ElementaryTypeName",
                  "src": "1048:7:28",
                  "stateMutability": "nonpayable",
                  "typeDescriptions": {
                    "typeIdentifier": "t_address",
                    "typeString": "address"
                  }
                },
                "visibility": "internal"
              }
            ],
            "src": "1047:17:28"
          }
        },
        {
          "id": 7665,
          "nodeType": "ErrorDefinition",
          "src": "1148:38:28",
          "nodes": [],
          "documentation": {
            "id": 7661,
            "nodeType": "StructuredDocumentation",
            "src": "1071:72:28",
            "text": "@dev Token is non-delegatable.\n @param account Token address."
          },
          "errorSelector": "535db4ec",
          "name": "NonDelegatable",
          "nameLocation": "1154:14:28",
          "parameters": {
            "id": 7664,
            "nodeType": "ParameterList",
            "parameters": [
              {
                "constant": false,
                "id": 7663,
                "mutability": "mutable",
                "name": "account",
                "nameLocation": "1177:7:28",
                "nodeType": "VariableDeclaration",
                "scope": 7665,
                "src": "1169:15:28",
                "stateVariable": false,
                "storageLocation": "default",
                "typeDescriptions": {
                  "typeIdentifier": "t_address",
                  "typeString": "address"
                },
                "typeName": {
                  "id": 7662,
                  "name": "address",
                  "nodeType": "ElementaryTypeName",
                  "src": "1169:7:28",
                  "stateMutability": "nonpayable",
                  "typeDescriptions": {
                    "typeIdentifier": "t_address",
                    "typeString": "address"
                  }
                },
                "visibility": "internal"
              }
            ],
            "src": "1168:17:28"
          }
        },
        {
          "id": 7672,
          "nodeType": "ErrorDefinition",
          "src": "1325:64:28",
          "nodes": [],
          "documentation": {
            "id": 7666,
            "nodeType": "StructuredDocumentation",
            "src": "1192:128:28",
            "text": "@dev Insufficient token allowance.\n @param provided Provided amount.\n @param expected Minimum expected amount."
          },
          "errorSelector": "2a1b2dd8",
          "name": "InsufficientAllowance",
          "nameLocation": "1331:21:28",
          "parameters": {
            "id": 7671,
            "nodeType": "ParameterList",
            "parameters": [
              {
                "constant": false,
                "id": 7668,
                "mutability": "mutable",
                "name": "provided",
                "nameLocation": "1361:8:28",
                "nodeType": "VariableDeclaration",
                "scope": 7672,
                "src": "1353:16:28",
                "stateVariable": false,
                "storageLocation": "default",
                "typeDescriptions": {
                  "typeIdentifier": "t_uint256",
                  "typeString": "uint256"
                },
                "typeName": {
                  "id": 7667,
                  "name": "uint256",
                  "nodeType": "ElementaryTypeName",
                  "src": "1353:7:28",
                  "typeDescriptions": {
                    "typeIdentifier": "t_uint256",
                    "typeString": "uint256"
                  }
                },
                "visibility": "internal"
              },
              {
                "constant": false,
                "id": 7670,
                "mutability": "mutable",
                "name": "expected",
                "nameLocation": "1379:8:28",
                "nodeType": "VariableDeclaration",
                "scope": 7672,
                "src": "1371:16:28",
                "stateVariable": false,
                "storageLocation": "default",
                "typeDescriptions": {
                  "typeIdentifier": "t_uint256",
                  "typeString": "uint256"
                },
                "typeName": {
                  "id": 7669,
                  "name": "uint256",
                  "nodeType": "ElementaryTypeName",
                  "src": "1371:7:28",
                  "typeDescriptions": {
                    "typeIdentifier": "t_uint256",
                    "typeString": "uint256"
                  }
                },
                "visibility": "internal"
              }
            ],
            "src": "1352:36:28"
          }
        },
        {
          "id": 7677,
          "nodeType": "ErrorDefinition",
          "src": "1510:37:28",
          "nodes": [],
          "documentation": {
            "id": 7673,
            "nodeType": "StructuredDocumentation",
            "src": "1395:110:28",
            "text": "@dev No existing lock value is found.\n @param account Address that is checked for the locked value."
          },
          "errorSelector": "1ff847b6",
          "name": "NoValueLocked",
          "nameLocation": "1516:13:28",
          "parameters": {
            "id": 7676,
            "nodeType": "ParameterList",
            "parameters": [
              {
                "constant": false,
                "id": 7675,
                "mutability": "mutable",
                "name": "account",
                "nameLocation": "1538:7:28",
                "nodeType": "VariableDeclaration",
                "scope": 7677,
                "src": "1530:15:28",
                "stateVariable": false,
                "storageLocation": "default",
                "typeDescriptions": {
                  "typeIdentifier": "t_address",
                  "typeString": "address"
                },
                "typeName": {
                  "id": 7674,
                  "name": "address",
                  "nodeType": "ElementaryTypeName",
                  "src": "1530:7:28",
                  "stateMutability": "nonpayable",
                  "typeDescriptions": {
                    "typeIdentifier": "t_address",
                    "typeString": "address"
                  }
                },
                "visibility": "internal"
              }
            ],
            "src": "1529:17:28"
          }
        },
        {
          "id": 7684,
          "nodeType": "ErrorDefinition",
          "src": "1698:58:28",
          "nodes": [],
          "documentation": {
            "id": 7678,
            "nodeType": "StructuredDocumentation",
            "src": "1553:140:28",
            "text": "@dev Locked value is not zero.\n @param account Address that is checked for the locked value.\n @param amount Locked amount."
          },
          "errorSelector": "89bf64dd",
          "name": "LockedValueNotZero",
          "nameLocation": "1704:18:28",
          "parameters": {
            "id": 7683,
            "nodeType": "ParameterList",
            "parameters": [
              {
                "constant": false,
                "id": 7680,
                "mutability": "mutable",
                "name": "account",
                "nameLocation": "1731:7:28",
                "nodeType": "VariableDeclaration",
                "scope": 7684,
                "src": "1723:15:28",
                "stateVariable": false,
                "storageLocation": "default",
                "typeDescriptions": {
                  "typeIdentifier": "t_address",
                  "typeString": "address"
                },
                "typeName": {
                  "id": 7679,
                  "name": "address",
                  "nodeType": "ElementaryTypeName",
                  "src": "1723:7:28",
                  "stateMutability": "nonpayable",
                  "typeDescriptions": {
                    "typeIdentifier": "t_address",
                    "typeString": "address"
                  }
                },
                "visibility": "internal"
              },
              {
                "constant": false,
                "id": 7682,
                "mutability": "mutable",
                "name": "amount",
                "nameLocation": "1748:6:28",
                "nodeType": "VariableDeclaration",
                "scope": 7684,
                "src": "1740:14:28",
                "stateVariable": false,
                "storageLocation": "default",
                "typeDescriptions": {
                  "typeIdentifier": "t_uint256",
                  "typeString": "uint256"
                },
                "typeName": {
                  "id": 7681,
                  "name": "uint256",
                  "nodeType": "ElementaryTypeName",
                  "src": "1740:7:28",
                  "typeDescriptions": {
                    "typeIdentifier": "t_uint256",
                    "typeString": "uint256"
                  }
                },
                "visibility": "internal"
              }
            ],
            "src": "1722:33:28"
          }
        },
        {
          "id": 7693,
          "nodeType": "ErrorDefinition",
          "src": "1963:70:28",
          "nodes": [],
          "documentation": {
            "id": 7685,
            "nodeType": "StructuredDocumentation",
            "src": "1762:196:28",
            "text": "@dev Value lock is expired.\n @param account Address that is checked for the locked value.\n @param deadline The lock expiration deadline.\n @param curTime Current timestamp."
          },
          "errorSelector": "d78507e1",
          "name": "LockExpired",
          "nameLocation": "1969:11:28",
          "parameters": {
            "id": 7692,
            "nodeType": "ParameterList",
            "parameters": [
              {
                "constant": false,
                "id": 7687,
                "mutability": "mutable",
                "name": "account",
                "nameLocation": "1989:7:28",
                "nodeType": "VariableDeclaration",
                "scope": 7693,
                "src": "1981:15:28",
                "stateVariable": false,
                "storageLocation": "default",
                "typeDescriptions": {
                  "typeIdentifier": "t_address",
                  "typeString": "address"
                },
                "typeName": {
                  "id": 7686,
                  "name": "address",
                  "nodeType": "ElementaryTypeName",
                  "src": "1981:7:28",
                  "stateMutability": "nonpayable",
                  "typeDescriptions": {
                    "typeIdentifier": "t_address",
                    "typeString": "address"
                  }
                },
                "visibility": "internal"
              },
              {
                "constant": false,
                "id": 7689,
                "mutability": "mutable",
                "name": "deadline",
                "nameLocation": "2006:8:28",
                "nodeType": "VariableDeclaration",
                "scope": 7693,
                "src": "1998:16:28",
                "stateVariable": false,
                "storageLocation": "default",
                "typeDescriptions": {
                  "typeIdentifier": "t_uint256",
                  "typeString": "uint256"
                },
                "typeName": {
                  "id": 7688,
                  "name": "uint256",
                  "nodeType": "ElementaryTypeName",
                  "src": "1998:7:28",
                  "typeDescriptions": {
                    "typeIdentifier": "t_uint256",
                    "typeString": "uint256"
                  }
                },
                "visibility": "internal"
              },
              {
                "constant": false,
                "id": 7691,
                "mutability": "mutable",
                "name": "curTime",
                "nameLocation": "2024:7:28",
                "nodeType": "VariableDeclaration",
                "scope": 7693,
                "src": "2016:15:28",
                "stateVariable": false,
                "storageLocation": "default",
                "typeDescriptions": {
                  "typeIdentifier": "t_uint256",
                  "typeString": "uint256"
                },
                "typeName": {
                  "id": 7690,
                  "name": "uint256",
                  "nodeType": "ElementaryTypeName",
                  "src": "2016:7:28",
                  "typeDescriptions": {
                    "typeIdentifier": "t_uint256",
                    "typeString": "uint256"
                  }
                },
                "visibility": "internal"
              }
            ],
            "src": "1980:52:28"
          }
        },
        {
          "id": 7702,
          "nodeType": "ErrorDefinition",
          "src": "2244:73:28",
          "nodes": [],
          "documentation": {
            "id": 7694,
            "nodeType": "StructuredDocumentation",
            "src": "2039:200:28",
            "text": "@dev Value lock is not expired.\n @param account Address that is checked for the locked value.\n @param deadline The lock expiration deadline.\n @param curTime Current timestamp."
          },
          "errorSelector": "ab0246b3",
          "name": "LockNotExpired",
          "nameLocation": "2250:14:28",
          "parameters": {
            "id": 7701,
            "nodeType": "ParameterList",
            "parameters": [
              {
                "constant": false,
                "id": 7696,
                "mutability": "mutable",
                "name": "account",
                "nameLocation": "2273:7:28",
                "nodeType": "VariableDeclaration",
                "scope": 7702,
                "src": "2265:15:28",
                "stateVariable": false,
                "storageLocation": "default",
                "typeDescriptions": {
                  "typeIdentifier": "t_address",
                  "typeString": "address"
                },
                "typeName": {
                  "id": 7695,
                  "name": "address",
                  "nodeType": "ElementaryTypeName",
                  "src": "2265:7:28",
                  "stateMutability": "nonpayable",
                  "typeDescriptions": {
                    "typeIdentifier": "t_address",
                    "typeString": "address"
                  }
                },
                "visibility": "internal"
              },
              {
                "constant": false,
                "id": 7698,
                "mutability": "mutable",
                "name": "deadline",
                "nameLocation": "2290:8:28",
                "nodeType": "VariableDeclaration",
                "scope": 7702,
                "src": "2282:16:28",
                "stateVariable": false,
                "storageLocation": "default",
                "typeDescriptions": {
                  "typeIdentifier": "t_uint256",
                  "typeString": "uint256"
                },
                "typeName": {
                  "id": 7697,
                  "name": "uint256",
                  "nodeType": "ElementaryTypeName",
                  "src": "2282:7:28",
                  "typeDescriptions": {
                    "typeIdentifier": "t_uint256",
                    "typeString": "uint256"
                  }
                },
                "visibility": "internal"
              },
              {
                "constant": false,
                "id": 7700,
                "mutability": "mutable",
                "name": "curTime",
                "nameLocation": "2308:7:28",
                "nodeType": "VariableDeclaration",
                "scope": 7702,
                "src": "2300:15:28",
                "stateVariable": false,
                "storageLocation": "default",
                "typeDescriptions": {
                  "typeIdentifier": "t_uint256",
                  "typeString": "uint256"
                },
                "typeName": {
                  "id": 7699,
                  "name": "uint256",
                  "nodeType": "ElementaryTypeName",
                  "src": "2300:7:28",
                  "typeDescriptions": {
                    "typeIdentifier": "t_uint256",
                    "typeString": "uint256"
                  }
                },
                "visibility": "internal"
              }
            ],
            "src": "2264:52:28"
          }
        },
        {
          "id": 7711,
          "nodeType": "ErrorDefinition",
          "src": "2562:94:28",
          "nodes": [],
          "documentation": {
            "id": 7703,
            "nodeType": "StructuredDocumentation",
            "src": "2323:234:28",
            "text": "@dev Provided unlock time is incorrect.\n @param account Address that is checked for the locked value.\n @param minUnlockTime Minimal unlock time that can be set.\n @param providedUnlockTime Provided unlock time."
          },
          "errorSelector": "311d1bf9",
          "name": "UnlockTimeIncorrect",
          "nameLocation": "2568:19:28",
          "parameters": {
            "id": 7710,
            "nodeType": "ParameterList",
            "parameters": [
              {
                "constant": false,
                "id": 7705,
                "mutability": "mutable",
                "name": "account",
                "nameLocation": "2596:7:28",
                "nodeType": "VariableDeclaration",
                "scope": 7711,
                "src": "2588:15:28",
                "stateVariable": false,
                "storageLocation": "default",
                "typeDescriptions": {
                  "typeIdentifier": "t_address",
                  "typeString": "address"
                },
                "typeName": {
                  "id": 7704,
                  "name": "address",
                  "nodeType": "ElementaryTypeName",
                  "src": "2588:7:28",
                  "stateMutability": "nonpayable",
                  "typeDescriptions": {
                    "typeIdentifier": "t_address",
                    "typeString": "address"
                  }
                },
                "visibility": "internal"
              },
              {
                "constant": false,
                "id": 7707,
                "mutability": "mutable",
                "name": "minUnlockTime",
                "nameLocation": "2613:13:28",
                "nodeType": "VariableDeclaration",
                "scope": 7711,
                "src": "2605:21:28",
                "stateVariable": false,
                "storageLocation": "default",
                "typeDescriptions": {
                  "typeIdentifier": "t_uint256",
                  "typeString": "uint256"
                },
                "typeName": {
                  "id": 7706,
                  "name": "uint256",
                  "nodeType": "ElementaryTypeName",
                  "src": "2605:7:28",
                  "typeDescriptions": {
                    "typeIdentifier": "t_uint256",
                    "typeString": "uint256"
                  }
                },
                "visibility": "internal"
              },
              {
                "constant": false,
                "id": 7709,
                "mutability": "mutable",
                "name": "providedUnlockTime",
                "nameLocation": "2636:18:28",
                "nodeType": "VariableDeclaration",
                "scope": 7711,
                "src": "2628:26:28",
                "stateVariable": false,
                "storageLocation": "default",
                "typeDescriptions": {
                  "typeIdentifier": "t_uint256",
                  "typeString": "uint256"
                },
                "typeName": {
                  "id": 7708,
                  "name": "uint256",
                  "nodeType": "ElementaryTypeName",
                  "src": "2628:7:28",
                  "typeDescriptions": {
                    "typeIdentifier": "t_uint256",
                    "typeString": "uint256"
                  }
                },
                "visibility": "internal"
              }
            ],
            "src": "2587:68:28"
          }
        },
        {
          "id": 7720,
          "nodeType": "ErrorDefinition",
          "src": "2919:95:28",
          "nodes": [],
          "documentation": {
            "id": 7712,
            "nodeType": "StructuredDocumentation",
            "src": "2662:252:28",
            "text": "@dev Provided unlock time is bigger than the maximum allowed.\n @param account Address that is checked for the locked value.\n @param maxUnlockTime Max unlock time that can be set.\n @param providedUnlockTime Provided unlock time."
          },
          "errorSelector": "c172987b",
          "name": "MaxUnlockTimeReached",
          "nameLocation": "2925:20:28",
          "parameters": {
            "id": 7719,
            "nodeType": "ParameterList",
            "parameters": [
              {
                "constant": false,
                "id": 7714,
                "mutability": "mutable",
                "name": "account",
                "nameLocation": "2954:7:28",
                "nodeType": "VariableDeclaration",
                "scope": 7720,
                "src": "2946:15:28",
                "stateVariable": false,
                "storageLocation": "default",
                "typeDescriptions": {
                  "typeIdentifier": "t_address",
                  "typeString": "address"
                },
                "typeName": {
                  "id": 7713,
                  "name": "address",
                  "nodeType": "ElementaryTypeName",
                  "src": "2946:7:28",
                  "stateMutability": "nonpayable",
                  "typeDescriptions": {
                    "typeIdentifier": "t_address",
                    "typeString": "address"
                  }
                },
                "visibility": "internal"
              },
              {
                "constant": false,
                "id": 7716,
                "mutability": "mutable",
                "name": "maxUnlockTime",
                "nameLocation": "2971:13:28",
                "nodeType": "VariableDeclaration",
                "scope": 7720,
                "src": "2963:21:28",
                "stateVariable": false,
                "storageLocation": "default",
                "typeDescriptions": {
                  "typeIdentifier": "t_uint256",
                  "typeString": "uint256"
                },
                "typeName": {
                  "id": 7715,
                  "name": "uint256",
                  "nodeType": "ElementaryTypeName",
                  "src": "2963:7:28",
                  "typeDescriptions": {
                    "typeIdentifier": "t_uint256",
                    "typeString": "uint256"
                  }
                },
                "visibility": "internal"
              },
              {
                "constant": false,
                "id": 7718,
                "mutability": "mutable",
                "name": "providedUnlockTime",
                "nameLocation": "2994:18:28",
                "nodeType": "VariableDeclaration",
                "scope": 7720,
                "src": "2986:26:28",
                "stateVariable": false,
                "storageLocation": "default",
                "typeDescriptions": {
                  "typeIdentifier": "t_uint256",
                  "typeString": "uint256"
                },
                "typeName": {
                  "id": 7717,
                  "name": "uint256",
                  "nodeType": "ElementaryTypeName",
                  "src": "2986:7:28",
                  "typeDescriptions": {
                    "typeIdentifier": "t_uint256",
                    "typeString": "uint256"
                  }
                },
                "visibility": "internal"
              }
            ],
            "src": "2945:68:28"
          }
        },
        {
          "id": 7727,
          "nodeType": "ErrorDefinition",
          "src": "3210:79:28",
          "nodes": [],
          "documentation": {
            "id": 7721,
            "nodeType": "StructuredDocumentation",
            "src": "3020:185:28",
            "text": "@dev Provided block number is incorrect (has not been processed yet).\n @param providedBlockNumber Provided block number.\n @param actualBlockNumber Actual block number."
          },
          "errorSelector": "8633967e",
          "name": "WrongBlockNumber",
          "nameLocation": "3216:16:28",
          "parameters": {
            "id": 7726,
            "nodeType": "ParameterList",
            "parameters": [
              {
                "constant": false,
                "id": 7723,
                "mutability": "mutable",
                "name": "providedBlockNumber",
                "nameLocation": "3241:19:28",
                "nodeType": "VariableDeclaration",
                "scope": 7727,
                "src": "3233:27:28",
                "stateVariable": false,
                "storageLocation": "default",
                "typeDescriptions": {
                  "typeIdentifier": "t_uint256",
                  "typeString": "uint256"
                },
                "typeName": {
                  "id": 7722,
                  "name": "uint256",
                  "nodeType": "ElementaryTypeName",
                  "src": "3233:7:28",
                  "typeDescriptions": {
                    "typeIdentifier": "t_uint256",
                    "typeString": "uint256"
                  }
                },
                "visibility": "internal"
              },
              {
                "constant": false,
                "id": 7725,
                "mutability": "mutable",
                "name": "actualBlockNumber",
                "nameLocation": "3270:17:28",
                "nodeType": "VariableDeclaration",
                "scope": 7727,
                "src": "3262:25:28",
                "stateVariable": false,
                "storageLocation": "default",
                "typeDescriptions": {
                  "typeIdentifier": "t_uint256",
                  "typeString": "uint256"
                },
                "typeName": {
                  "id": 7724,
                  "name": "uint256",
                  "nodeType": "ElementaryTypeName",
                  "src": "3262:7:28",
                  "typeDescriptions": {
                    "typeIdentifier": "t_uint256",
                    "typeString": "uint256"
                  }
                },
                "visibility": "internal"
              }
            ],
            "src": "3232:56:28"
          }
        }
      ],
      "abstract": false,
      "baseContracts": [],
      "canonicalName": "IErrors",
      "contractDependencies": [],
      "contractKind": "interface",
      "documentation": {
        "id": 7625,
        "nodeType": "StructuredDocumentation",
        "src": "58:17:28",
        "text": "@dev Errors."
      },
      "fullyImplemented": true,
      "linearizedBaseContracts": [
        7728
      ],
      "name": "IErrors",
      "nameLocation": "85:7:28",
      "scope": 7729,
      "usedErrors": [
        7632,
        7635,
        7638,
        7641,
        7648,
        7655,
        7660,
        7665,
        7672,
        7677,
        7684,
        7693,
        7702,
        7711,
        7720,
        7727
      ],
      "usedEvents": []
    }
  ],
  "license": "MIT"
}