{
  "absolutePath": "lib/openzeppelin-contracts-upgradeable/contracts/utils/ReentrancyGuardTransientUpgradeable.sol",
  "id": 46984,
  "exportedSymbols": {
    "Initializable": [
      45141
    ],
    "ReentrancyGuardTransientUpgradeable": [
      46983
    ],
    "TransientSlot": [
      52256
    ]
  },
  "nodeType": "SourceUnit",
  "src": "118:2267:30",
  "nodes": [
    {
      "id": 46900,
      "nodeType": "PragmaDirective",
      "src": "118:24:30",
      "nodes": [],
      "literals": [
        "solidity",
        "^",
        "0.8",
        ".24"
      ]
    },
    {
      "id": 46902,
      "nodeType": "ImportDirective",
      "src": "144:78:30",
      "nodes": [],
      "absolutePath": "lib/openzeppelin-contracts-upgradeable/lib/openzeppelin-contracts/contracts/utils/TransientSlot.sol",
      "file": "@openzeppelin/contracts/utils/TransientSlot.sol",
      "nameLocation": "-1:-1:-1",
      "scope": 46984,
      "sourceUnit": 52257,
      "symbolAliases": [
        {
          "foreign": {
            "id": 46901,
            "name": "TransientSlot",
            "nodeType": "Identifier",
            "overloadedDeclarations": [],
            "referencedDeclaration": 52256,
            "src": "152:13:30",
            "typeDescriptions": {}
          },
          "nameLocation": "-1:-1:-1"
        }
      ],
      "unitAlias": ""
    },
    {
      "id": 46904,
      "nodeType": "ImportDirective",
      "src": "223:63:30",
      "nodes": [],
      "absolutePath": "lib/openzeppelin-contracts-upgradeable/contracts/proxy/utils/Initializable.sol",
      "file": "../proxy/utils/Initializable.sol",
      "nameLocation": "-1:-1:-1",
      "scope": 46984,
      "sourceUnit": 45142,
      "symbolAliases": [
        {
          "foreign": {
            "id": 46903,
            "name": "Initializable",
            "nodeType": "Identifier",
            "overloadedDeclarations": [],
            "referencedDeclaration": 45141,
            "src": "231:13:30",
            "typeDescriptions": {}
          },
          "nameLocation": "-1:-1:-1"
        }
      ],
      "unitAlias": ""
    },
    {
      "id": 46983,
      "nodeType": "ContractDefinition",
      "src": "469:1915:30",
      "nodes": [
        {
          "id": 46909,
          "nodeType": "UsingForDirective",
          "src": "546:26:30",
          "nodes": [],
          "global": false,
          "libraryName": {
            "id": 46908,
            "name": "TransientSlot",
            "nameLocations": [
              "552:13:30"
            ],
            "nodeType": "IdentifierPath",
            "referencedDeclaration": 52256,
            "src": "552:13:30"
          }
        },
        {
          "id": 46912,
          "nodeType": "VariableDeclaration",
          "src": "697:126:30",
          "nodes": [],
          "constant": true,
          "mutability": "constant",
          "name": "REENTRANCY_GUARD_STORAGE",
          "nameLocation": "722:24:30",
          "scope": 46983,
          "stateVariable": true,
          "storageLocation": "default",
          "typeDescriptions": {
            "typeIdentifier": "t_bytes32",
            "typeString": "bytes32"
          },
          "typeName": {
            "id": 46910,
            "name": "bytes32",
            "nodeType": "ElementaryTypeName",
            "src": "697:7:30",
            "typeDescriptions": {
              "typeIdentifier": "t_bytes32",
              "typeString": "bytes32"
            }
          },
          "value": {
            "hexValue": "307839623737396231373432326430646639323232333031386233326234643166613436653037313732336436383137653234383664303033626563633535663030",
            "id": 46911,
            "isConstant": false,
            "isLValue": false,
            "isPure": true,
            "kind": "number",
            "lValueRequested": false,
            "nodeType": "Literal",
            "src": "757:66:30",
            "typeDescriptions": {
              "typeIdentifier": "t_rational_70319816728846589445362000750570655803700195216363692647688146666176345628416_by_1",
              "typeString": "int_const 7031...(69 digits omitted)...8416"
            },
            "value": "0x9b779b17422d0df92223018b32b4d1fa46e071723d6817e2486d003becc55f00"
          },
          "visibility": "private"
        },
        {
          "id": 46915,
          "nodeType": "ErrorDefinition",
          "src": "887:37:30",
          "nodes": [],
          "documentation": {
            "id": 46913,
            "nodeType": "StructuredDocumentation",
            "src": "830:52:30",
            "text": " @dev Unauthorized reentrant call."
          },
          "errorSelector": "3ee5aeb5",
          "name": "ReentrancyGuardReentrantCall",
          "nameLocation": "893:28:30",
          "parameters": {
            "id": 46914,
            "nodeType": "ParameterList",
            "parameters": [],
            "src": "921:2:30"
          }
        },
        {
          "id": 46926,
          "nodeType": "ModifierDefinition",
          "src": "1301:103:30",
          "nodes": [],
          "body": {
            "id": 46925,
            "nodeType": "Block",
            "src": "1325:79:30",
            "nodes": [],
            "statements": [
              {
                "expression": {
                  "arguments": [],
                  "expression": {
                    "argumentTypes": [],
                    "id": 46918,
                    "name": "_nonReentrantBefore",
                    "nodeType": "Identifier",
                    "overloadedDeclarations": [],
                    "referencedDeclaration": 46957,
                    "src": "1335:19:30",
                    "typeDescriptions": {
                      "typeIdentifier": "t_function_internal_nonpayable$__$returns$__$",
                      "typeString": "function ()"
                    }
                  },
                  "id": 46919,
                  "isConstant": false,
                  "isLValue": false,
                  "isPure": false,
                  "kind": "functionCall",
                  "lValueRequested": false,
                  "nameLocations": [],
                  "names": [],
                  "nodeType": "FunctionCall",
                  "src": "1335:21:30",
                  "tryCall": false,
                  "typeDescriptions": {
                    "typeIdentifier": "t_tuple$__$",
                    "typeString": "tuple()"
                  }
                },
                "id": 46920,
                "nodeType": "ExpressionStatement",
                "src": "1335:21:30"
              },
              {
                "id": 46921,
                "nodeType": "PlaceholderStatement",
                "src": "1366:1:30"
              },
              {
                "expression": {
                  "arguments": [],
                  "expression": {
                    "argumentTypes": [],
                    "id": 46922,
                    "name": "_nonReentrantAfter",
                    "nodeType": "Identifier",
                    "overloadedDeclarations": [],
                    "referencedDeclaration": 46969,
                    "src": "1377:18:30",
                    "typeDescriptions": {
                      "typeIdentifier": "t_function_internal_nonpayable$__$returns$__$",
                      "typeString": "function ()"
                    }
                  },
                  "id": 46923,
                  "isConstant": false,
                  "isLValue": false,
                  "isPure": false,
                  "kind": "functionCall",
                  "lValueRequested": false,
                  "nameLocations": [],
                  "names": [],
                  "nodeType": "FunctionCall",
                  "src": "1377:20:30",
                  "tryCall": false,
                  "typeDescriptions": {
                    "typeIdentifier": "t_tuple$__$",
                    "typeString": "tuple()"
                  }
                },
                "id": 46924,
                "nodeType": "ExpressionStatement",
                "src": "1377:20:30"
              }
            ]
          },
          "documentation": {
            "id": 46916,
            "nodeType": "StructuredDocumentation",
            "src": "930:366:30",
            "text": " @dev Prevents a contract from calling itself, directly or indirectly.\n Calling a `nonReentrant` function from another `nonReentrant`\n function is not supported. It is possible to prevent this from happening\n by making the `nonReentrant` function external, and making it call a\n `private` function that does the actual work."
          },
          "name": "nonReentrant",
          "nameLocation": "1310:12:30",
          "parameters": {
            "id": 46917,
            "nodeType": "ParameterList",
            "parameters": [],
            "src": "1322:2:30"
          },
          "virtual": false,
          "visibility": "internal"
        },
        {
          "id": 46932,
          "nodeType": "FunctionDefinition",
          "src": "1410:76:30",
          "nodes": [],
          "body": {
            "id": 46931,
            "nodeType": "Block",
            "src": "1479:7:30",
            "nodes": [],
            "statements": []
          },
          "implemented": true,
          "kind": "function",
          "modifiers": [
            {
              "id": 46929,
              "kind": "modifierInvocation",
              "modifierName": {
                "id": 46928,
                "name": "onlyInitializing",
                "nameLocations": [
                  "1462:16:30"
                ],
                "nodeType": "IdentifierPath",
                "referencedDeclaration": 45036,
                "src": "1462:16:30"
              },
              "nodeType": "ModifierInvocation",
              "src": "1462:16:30"
            }
          ],
          "name": "__ReentrancyGuardTransient_init",
          "nameLocation": "1419:31:30",
          "parameters": {
            "id": 46927,
            "nodeType": "ParameterList",
            "parameters": [],
            "src": "1450:2:30"
          },
          "returnParameters": {
            "id": 46930,
            "nodeType": "ParameterList",
            "parameters": [],
            "src": "1479:0:30"
          },
          "scope": 46983,
          "stateMutability": "nonpayable",
          "virtual": false,
          "visibility": "internal"
        },
        {
          "id": 46938,
          "nodeType": "FunctionDefinition",
          "src": "1492:86:30",
          "nodes": [],
          "body": {
            "id": 46937,
            "nodeType": "Block",
            "src": "1571:7:30",
            "nodes": [],
            "statements": []
          },
          "implemented": true,
          "kind": "function",
          "modifiers": [
            {
              "id": 46935,
              "kind": "modifierInvocation",
              "modifierName": {
                "id": 46934,
                "name": "onlyInitializing",
                "nameLocations": [
                  "1554:16:30"
                ],
                "nodeType": "IdentifierPath",
                "referencedDeclaration": 45036,
                "src": "1554:16:30"
              },
              "nodeType": "ModifierInvocation",
              "src": "1554:16:30"
            }
          ],
          "name": "__ReentrancyGuardTransient_init_unchained",
          "nameLocation": "1501:41:30",
          "parameters": {
            "id": 46933,
            "nodeType": "ParameterList",
            "parameters": [],
            "src": "1542:2:30"
          },
          "returnParameters": {
            "id": 46936,
            "nodeType": "ParameterList",
            "parameters": [],
            "src": "1571:0:30"
          },
          "scope": 46983,
          "stateMutability": "nonpayable",
          "virtual": false,
          "visibility": "internal"
        },
        {
          "id": 46957,
          "nodeType": "FunctionDefinition",
          "src": "1583:377:30",
          "nodes": [],
          "body": {
            "id": 46956,
            "nodeType": "Block",
            "src": "1622:338:30",
            "nodes": [],
            "statements": [
              {
                "condition": {
                  "arguments": [],
                  "expression": {
                    "argumentTypes": [],
                    "id": 46941,
                    "name": "_reentrancyGuardEntered",
                    "nodeType": "Identifier",
                    "overloadedDeclarations": [],
                    "referencedDeclaration": 46982,
                    "src": "1741:23:30",
                    "typeDescriptions": {
                      "typeIdentifier": "t_function_internal_view$__$returns$_t_bool_$",
                      "typeString": "function () view returns (bool)"
                    }
                  },
                  "id": 46942,
                  "isConstant": false,
                  "isLValue": false,
                  "isPure": false,
                  "kind": "functionCall",
                  "lValueRequested": false,
                  "nameLocations": [],
                  "names": [],
                  "nodeType": "FunctionCall",
                  "src": "1741:25:30",
                  "tryCall": false,
                  "typeDescriptions": {
                    "typeIdentifier": "t_bool",
                    "typeString": "bool"
                  }
                },
                "id": 46947,
                "nodeType": "IfStatement",
                "src": "1737:93:30",
                "trueBody": {
                  "id": 46946,
                  "nodeType": "Block",
                  "src": "1768:62:30",
                  "statements": [
                    {
                      "errorCall": {
                        "arguments": [],
                        "expression": {
                          "argumentTypes": [],
                          "id": 46943,
                          "name": "ReentrancyGuardReentrantCall",
                          "nodeType": "Identifier",
                          "overloadedDeclarations": [],
                          "referencedDeclaration": 46915,
                          "src": "1789:28:30",
                          "typeDescriptions": {
                            "typeIdentifier": "t_function_error_pure$__$returns$_t_error_$",
                            "typeString": "function () pure returns (error)"
                          }
                        },
                        "id": 46944,
                        "isConstant": false,
                        "isLValue": false,
                        "isPure": false,
                        "kind": "functionCall",
                        "lValueRequested": false,
                        "nameLocations": [],
                        "names": [],
                        "nodeType": "FunctionCall",
                        "src": "1789:30:30",
                        "tryCall": false,
                        "typeDescriptions": {
                          "typeIdentifier": "t_error",
                          "typeString": "error"
                        }
                      },
                      "id": 46945,
                      "nodeType": "RevertStatement",
                      "src": "1782:37:30"
                    }
                  ]
                }
              },
              {
                "expression": {
                  "arguments": [
                    {
                      "hexValue": "74727565",
                      "id": 46953,
                      "isConstant": false,
                      "isLValue": false,
                      "isPure": true,
                      "kind": "bool",
                      "lValueRequested": false,
                      "nodeType": "Literal",
                      "src": "1948:4:30",
                      "typeDescriptions": {
                        "typeIdentifier": "t_bool",
                        "typeString": "bool"
                      },
                      "value": "true"
                    }
                  ],
                  "expression": {
                    "argumentTypes": [
                      {
                        "typeIdentifier": "t_bool",
                        "typeString": "bool"
                      }
                    ],
                    "expression": {
                      "arguments": [],
                      "expression": {
                        "argumentTypes": [],
                        "expression": {
                          "id": 46948,
                          "name": "REENTRANCY_GUARD_STORAGE",
                          "nodeType": "Identifier",
                          "overloadedDeclarations": [],
                          "referencedDeclaration": 46912,
                          "src": "1904:24:30",
                          "typeDescriptions": {
                            "typeIdentifier": "t_bytes32",
                            "typeString": "bytes32"
                          }
                        },
                        "id": 46950,
                        "isConstant": false,
                        "isLValue": false,
                        "isPure": false,
                        "lValueRequested": false,
                        "memberLocation": "1929:9:30",
                        "memberName": "asBoolean",
                        "nodeType": "MemberAccess",
                        "referencedDeclaration": 52094,
                        "src": "1904:34:30",
                        "typeDescriptions": {
                          "typeIdentifier": "t_function_internal_pure$_t_bytes32_$returns$_t_userDefinedValueType$_BooleanSlot_$52079_$attached_to$_t_bytes32_$",
                          "typeString": "function (bytes32) pure returns (TransientSlot.BooleanSlot)"
                        }
                      },
                      "id": 46951,
                      "isConstant": false,
                      "isLValue": false,
                      "isPure": false,
                      "kind": "functionCall",
                      "lValueRequested": false,
                      "nameLocations": [],
                      "names": [],
                      "nodeType": "FunctionCall",
                      "src": "1904:36:30",
                      "tryCall": false,
                      "typeDescriptions": {
                        "typeIdentifier": "t_userDefinedValueType$_BooleanSlot_$52079",
                        "typeString": "TransientSlot.BooleanSlot"
                      }
                    },
                    "id": 46952,
                    "isConstant": false,
                    "isLValue": false,
                    "isPure": false,
                    "lValueRequested": false,
                    "memberLocation": "1941:6:30",
                    "memberName": "tstore",
                    "nodeType": "MemberAccess",
                    "referencedDeclaration": 52189,
                    "src": "1904:43:30",
                    "typeDescriptions": {
                      "typeIdentifier": "t_function_internal_nonpayable$_t_userDefinedValueType$_BooleanSlot_$52079_$_t_bool_$returns$__$attached_to$_t_userDefinedValueType$_BooleanSlot_$52079_$",
                      "typeString": "function (TransientSlot.BooleanSlot,bool)"
                    }
                  },
                  "id": 46954,
                  "isConstant": false,
                  "isLValue": false,
                  "isPure": false,
                  "kind": "functionCall",
                  "lValueRequested": false,
                  "nameLocations": [],
                  "names": [],
                  "nodeType": "FunctionCall",
                  "src": "1904:49:30",
                  "tryCall": false,
                  "typeDescriptions": {
                    "typeIdentifier": "t_tuple$__$",
                    "typeString": "tuple()"
                  }
                },
                "id": 46955,
                "nodeType": "ExpressionStatement",
                "src": "1904:49:30"
              }
            ]
          },
          "implemented": true,
          "kind": "function",
          "modifiers": [],
          "name": "_nonReentrantBefore",
          "nameLocation": "1592:19:30",
          "parameters": {
            "id": 46939,
            "nodeType": "ParameterList",
            "parameters": [],
            "src": "1611:2:30"
          },
          "returnParameters": {
            "id": 46940,
            "nodeType": "ParameterList",
            "parameters": [],
            "src": "1622:0:30"
          },
          "scope": 46983,
          "stateMutability": "nonpayable",
          "virtual": false,
          "visibility": "private"
        },
        {
          "id": 46969,
          "nodeType": "FunctionDefinition",
          "src": "1966:105:30",
          "nodes": [],
          "body": {
            "id": 46968,
            "nodeType": "Block",
            "src": "2004:67:30",
            "nodes": [],
            "statements": [
              {
                "expression": {
                  "arguments": [
                    {
                      "hexValue": "66616c7365",
                      "id": 46965,
                      "isConstant": false,
                      "isLValue": false,
                      "isPure": true,
                      "kind": "bool",
                      "lValueRequested": false,
                      "nodeType": "Literal",
                      "src": "2058:5:30",
                      "typeDescriptions": {
                        "typeIdentifier": "t_bool",
                        "typeString": "bool"
                      },
                      "value": "false"
                    }
                  ],
                  "expression": {
                    "argumentTypes": [
                      {
                        "typeIdentifier": "t_bool",
                        "typeString": "bool"
                      }
                    ],
                    "expression": {
                      "arguments": [],
                      "expression": {
                        "argumentTypes": [],
                        "expression": {
                          "id": 46960,
                          "name": "REENTRANCY_GUARD_STORAGE",
                          "nodeType": "Identifier",
                          "overloadedDeclarations": [],
                          "referencedDeclaration": 46912,
                          "src": "2014:24:30",
                          "typeDescriptions": {
                            "typeIdentifier": "t_bytes32",
                            "typeString": "bytes32"
                          }
                        },
                        "id": 46962,
                        "isConstant": false,
                        "isLValue": false,
                        "isPure": false,
                        "lValueRequested": false,
                        "memberLocation": "2039:9:30",
                        "memberName": "asBoolean",
                        "nodeType": "MemberAccess",
                        "referencedDeclaration": 52094,
                        "src": "2014:34:30",
                        "typeDescriptions": {
                          "typeIdentifier": "t_function_internal_pure$_t_bytes32_$returns$_t_userDefinedValueType$_BooleanSlot_$52079_$attached_to$_t_bytes32_$",
                          "typeString": "function (bytes32) pure returns (TransientSlot.BooleanSlot)"
                        }
                      },
                      "id": 46963,
                      "isConstant": false,
                      "isLValue": false,
                      "isPure": false,
                      "kind": "functionCall",
                      "lValueRequested": false,
                      "nameLocations": [],
                      "names": [],
                      "nodeType": "FunctionCall",
                      "src": "2014:36:30",
                      "tryCall": false,
                      "typeDescriptions": {
                        "typeIdentifier": "t_userDefinedValueType$_BooleanSlot_$52079",
                        "typeString": "TransientSlot.BooleanSlot"
                      }
                    },
                    "id": 46964,
                    "isConstant": false,
                    "isLValue": false,
                    "isPure": false,
                    "lValueRequested": false,
                    "memberLocation": "2051:6:30",
                    "memberName": "tstore",
                    "nodeType": "MemberAccess",
                    "referencedDeclaration": 52189,
                    "src": "2014:43:30",
                    "typeDescriptions": {
                      "typeIdentifier": "t_function_internal_nonpayable$_t_userDefinedValueType$_BooleanSlot_$52079_$_t_bool_$returns$__$attached_to$_t_userDefinedValueType$_BooleanSlot_$52079_$",
                      "typeString": "function (TransientSlot.BooleanSlot,bool)"
                    }
                  },
                  "id": 46966,
                  "isConstant": false,
                  "isLValue": false,
                  "isPure": false,
                  "kind": "functionCall",
                  "lValueRequested": false,
                  "nameLocations": [],
                  "names": [],
                  "nodeType": "FunctionCall",
                  "src": "2014:50:30",
                  "tryCall": false,
                  "typeDescriptions": {
                    "typeIdentifier": "t_tuple$__$",
                    "typeString": "tuple()"
                  }
                },
                "id": 46967,
                "nodeType": "ExpressionStatement",
                "src": "2014:50:30"
              }
            ]
          },
          "implemented": true,
          "kind": "function",
          "modifiers": [],
          "name": "_nonReentrantAfter",
          "nameLocation": "1975:18:30",
          "parameters": {
            "id": 46958,
            "nodeType": "ParameterList",
            "parameters": [],
            "src": "1993:2:30"
          },
          "returnParameters": {
            "id": 46959,
            "nodeType": "ParameterList",
            "parameters": [],
            "src": "2004:0:30"
          },
          "scope": 46983,
          "stateMutability": "nonpayable",
          "virtual": false,
          "visibility": "private"
        },
        {
          "id": 46982,
          "nodeType": "FunctionDefinition",
          "src": "2250:132:30",
          "nodes": [],
          "body": {
            "id": 46981,
            "nodeType": "Block",
            "src": "2314:68:30",
            "nodes": [],
            "statements": [
              {
                "expression": {
                  "arguments": [],
                  "expression": {
                    "argumentTypes": [],
                    "expression": {
                      "arguments": [],
                      "expression": {
                        "argumentTypes": [],
                        "expression": {
                          "id": 46975,
                          "name": "REENTRANCY_GUARD_STORAGE",
                          "nodeType": "Identifier",
                          "overloadedDeclarations": [],
                          "referencedDeclaration": 46912,
                          "src": "2331:24:30",
                          "typeDescriptions": {
                            "typeIdentifier": "t_bytes32",
                            "typeString": "bytes32"
                          }
                        },
                        "id": 46976,
                        "isConstant": false,
                        "isLValue": false,
                        "isPure": false,
                        "lValueRequested": false,
                        "memberLocation": "2356:9:30",
                        "memberName": "asBoolean",
                        "nodeType": "MemberAccess",
                        "referencedDeclaration": 52094,
                        "src": "2331:34:30",
                        "typeDescriptions": {
                          "typeIdentifier": "t_function_internal_pure$_t_bytes32_$returns$_t_userDefinedValueType$_BooleanSlot_$52079_$attached_to$_t_bytes32_$",
                          "typeString": "function (bytes32) pure returns (TransientSlot.BooleanSlot)"
                        }
                      },
                      "id": 46977,
                      "isConstant": false,
                      "isLValue": false,
                      "isPure": false,
                      "kind": "functionCall",
                      "lValueRequested": false,
                      "nameLocations": [],
                      "names": [],
                      "nodeType": "FunctionCall",
                      "src": "2331:36:30",
                      "tryCall": false,
                      "typeDescriptions": {
                        "typeIdentifier": "t_userDefinedValueType$_BooleanSlot_$52079",
                        "typeString": "TransientSlot.BooleanSlot"
                      }
                    },
                    "id": 46978,
                    "isConstant": false,
                    "isLValue": false,
                    "isPure": false,
                    "lValueRequested": false,
                    "memberLocation": "2368:5:30",
                    "memberName": "tload",
                    "nodeType": "MemberAccess",
                    "referencedDeclaration": 52178,
                    "src": "2331:42:30",
                    "typeDescriptions": {
                      "typeIdentifier": "t_function_internal_view$_t_userDefinedValueType$_BooleanSlot_$52079_$returns$_t_bool_$attached_to$_t_userDefinedValueType$_BooleanSlot_$52079_$",
                      "typeString": "function (TransientSlot.BooleanSlot) view returns (bool)"
                    }
                  },
                  "id": 46979,
                  "isConstant": false,
                  "isLValue": false,
                  "isPure": false,
                  "kind": "functionCall",
                  "lValueRequested": false,
                  "nameLocations": [],
                  "names": [],
                  "nodeType": "FunctionCall",
                  "src": "2331:44:30",
                  "tryCall": false,
                  "typeDescriptions": {
                    "typeIdentifier": "t_bool",
                    "typeString": "bool"
                  }
                },
                "functionReturnParameters": 46974,
                "id": 46980,
                "nodeType": "Return",
                "src": "2324:51:30"
              }
            ]
          },
          "documentation": {
            "id": 46970,
            "nodeType": "StructuredDocumentation",
            "src": "2077:168:30",
            "text": " @dev Returns true if the reentrancy guard is currently set to \"entered\", which indicates there is a\n `nonReentrant` function in the call stack."
          },
          "implemented": true,
          "kind": "function",
          "modifiers": [],
          "name": "_reentrancyGuardEntered",
          "nameLocation": "2259:23:30",
          "parameters": {
            "id": 46971,
            "nodeType": "ParameterList",
            "parameters": [],
            "src": "2282:2:30"
          },
          "returnParameters": {
            "id": 46974,
            "nodeType": "ParameterList",
            "parameters": [
              {
                "constant": false,
                "id": 46973,
                "mutability": "mutable",
                "name": "",
                "nameLocation": "-1:-1:-1",
                "nodeType": "VariableDeclaration",
                "scope": 46982,
                "src": "2308:4:30",
                "stateVariable": false,
                "storageLocation": "default",
                "typeDescriptions": {
                  "typeIdentifier": "t_bool",
                  "typeString": "bool"
                },
                "typeName": {
                  "id": 46972,
                  "name": "bool",
                  "nodeType": "ElementaryTypeName",
                  "src": "2308:4:30",
                  "typeDescriptions": {
                    "typeIdentifier": "t_bool",
                    "typeString": "bool"
                  }
                },
                "visibility": "internal"
              }
            ],
            "src": "2307:6:30"
          },
          "scope": 46983,
          "stateMutability": "view",
          "virtual": false,
          "visibility": "internal"
        }
      ],
      "abstract": true,
      "baseContracts": [
        {
          "baseName": {
            "id": 46906,
            "name": "Initializable",
            "nameLocations": [
              "526:13:30"
            ],
            "nodeType": "IdentifierPath",
            "referencedDeclaration": 45141,
            "src": "526:13:30"
          },
          "id": 46907,
          "nodeType": "InheritanceSpecifier",
          "src": "526:13:30"
        }
      ],
      "canonicalName": "ReentrancyGuardTransientUpgradeable",
      "contractDependencies": [],
      "contractKind": "contract",
      "documentation": {
        "id": 46905,
        "nodeType": "StructuredDocumentation",
        "src": "288:180:30",
        "text": " @dev Variant of {ReentrancyGuard} that uses transient storage.\n NOTE: This variant only works on networks where EIP-1153 is available.\n _Available since v5.1._"
      },
      "fullyImplemented": true,
      "linearizedBaseContracts": [
        46983,
        45141
      ],
      "name": "ReentrancyGuardTransientUpgradeable",
      "nameLocation": "487:35:30",
      "scope": 46984,
      "usedErrors": [
        44890,
        44893,
        46915
      ],
      "usedEvents": [
        44898
      ]
    }
  ],
  "license": "MIT"
}